Nucle/Cloud.py
Nucle/__init__.py
nucle.cloud-0.0.8.dist-info/LICENCE
nucle.cloud-0.0.8.dist-info/METADATA
nucle.cloud-0.0.8.dist-info/WHEEL
nucle.cloud-0.0.8.dist-info/top_level.txt
nucle.cloud-0.0.8.dist-info/RECORD
