Metadata-Version: 2.1
Name: nucle.cloud
Version: 0.0.8
Summary: The official Python library for Nucle Cloud service.
Author-email: Nucle Cloud <contact@nucle.cloud>
Project-URL: Homepage, https://nucle.cloud
Project-URL: Documentation, https://nucle.cloud/documentation/python
Project-URL: Repository, https://github.com/nuclecloud/python
Project-URL: Bug Tracker, https://github.com/nuclecloud/python/issues
Keywords: cloud,nucle,service,python,nucle.cloud,authentication,leaderboard,backend,restful,API,unity3d,unreal,godot
Classifier: Programming Language :: Python :: 3
Classifier: License :: OSI Approved :: MIT License
Classifier: Operating System :: OS Independent
Requires-Python: >=3.7
License-File: LICENCE
Requires-Dist: requests
